pipeline_ha/__init__.py
pipeline_ha/preprocessing_func.py
tests/__init__.py
tests/test_preprocessing.py
pipeline_ha-1.2.dist-info/METADATA
pipeline_ha-1.2.dist-info/WHEEL
pipeline_ha-1.2.dist-info/top_level.txt
pipeline_ha-1.2.dist-info/RECORD
