Metadata-Version: 2.1
Name: pipeline-ha
Version: 1.2
Summary: Package for NLP Pipeline
Home-page: UNKNOWN
Author: Himanshu Aditya
License: MIT
Platform: UNKNOWN
